cinelytics_sdk/__init__.py
cinelytics_sdk/film_client.py
cinelytics_sdk/film_config.py
cinelytics_sdk/schemas/__init__.py
cinelytics_sdk/schemas/schemas.py
cinelytics_sdk-0.1.1.dist-info/METADATA
cinelytics_sdk-0.1.1.dist-info/WHEEL
cinelytics_sdk-0.1.1.dist-info/top_level.txt
cinelytics_sdk-0.1.1.dist-info/RECORD
