Metadata-Version: 2.4
Name: cinelytics_sdk
Version: 0.1.1
Summary: SDK Python léger et intuitif pour interagir avec l'API CINEMA_INSIGHTS, conçu pour les Data Analysts et Data Scientists
Author-email: KADER KOUADIO <kkaderkouadio@gmail.com>
License: MIT
Classifier: Development Status :: 4 - Beta
Classifier: Intended Audience :: Developers
Classifier: Intended Audience :: Science/Research
Classifier: Programming Language :: Python :: 3
Classifier: License :: OSI Approved :: MIT License
Classifier: Operating System :: OS Independent
Classifier: Topic :: Software Development :: Libraries
Requires-Python: >=3.11
Requires-Dist: httpx>=0.28.1
Requires-Dist: pydantic>=2.11.3
Requires-Dist: backoff>=2.2.1
Requires-Dist: numpy>=2.2.4
Requires-Dist: pandas>=2.2.3
Requires-Dist: python-dotenv>=1.0.1
